{
  "mainAssemblyName": "Portfolio",
  "resources": {
    "hash": "sha256-FGxZw8o7cU713Pg/I0q/DdwzHQJBdNlXxbsT1QxWezw=",
    "fingerprinting": {
      "Microsoft.AspNetCore.Components.Forms.td9x62u7gn.wasm": "Microsoft.AspNetCore.Components.Forms.wasm",
      "Microsoft.AspNetCore.Components.1lkau6dtgw.wasm": "Microsoft.AspNetCore.Components.wasm",
      "Microsoft.AspNetCore.Components.Web.0ss19v5jlo.wasm": "Microsoft.AspNetCore.Components.Web.wasm",
      "Microsoft.AspNetCore.Components.WebAssembly.ifqb5azqz6.wasm": "Microsoft.AspNetCore.Components.WebAssembly.wasm",
      "Microsoft.Extensions.Configuration.Abstractions.n3roazub70.wasm": "Microsoft.Extensions.Configuration.Abstractions.wasm",
      "Microsoft.Extensions.Configuration.Json.jgtmx19396.wasm": "Microsoft.Extensions.Configuration.Json.wasm",
      "Microsoft.Extensions.Configuration.7sm4vp77d1.wasm": "Microsoft.Extensions.Configuration.wasm",
      "Microsoft.Extensions.DependencyInjection.Abstractions.hhm8pai5l9.wasm": "Microsoft.Extensions.DependencyInjection.Abstractions.wasm",
      "Microsoft.Extensions.DependencyInjection.g0r86u4i0h.wasm": "Microsoft.Extensions.DependencyInjection.wasm",
      "Microsoft.Extensions.Localization.Abstractions.sjbuahyqim.wasm": "Microsoft.Extensions.Localization.Abstractions.wasm",
      "Microsoft.Extensions.Localization.wgdl21ygqt.wasm": "Microsoft.Extensions.Localization.wasm",
      "Microsoft.Extensions.Logging.Abstractions.038440qxfw.wasm": "Microsoft.Extensions.Logging.Abstractions.wasm",
      "Microsoft.Extensions.Logging.km3zhtnk76.wasm": "Microsoft.Extensions.Logging.wasm",
      "Microsoft.Extensions.Options.x25gjdmbax.wasm": "Microsoft.Extensions.Options.wasm",
      "Microsoft.Extensions.Primitives.4dxofymb0o.wasm": "Microsoft.Extensions.Primitives.wasm",
      "Microsoft.JSInterop.to13l1w5p5.wasm": "Microsoft.JSInterop.wasm",
      "Microsoft.JSInterop.WebAssembly.p386u0jty9.wasm": "Microsoft.JSInterop.WebAssembly.wasm",
      "MudBlazor.dmkh4jnd06.wasm": "MudBlazor.wasm",
      "Portfolio.hv43xg6fnv.wasm": "Portfolio.wasm",
      "System.Collections.Concurrent.vvprmz0u6g.wasm": "System.Collections.Concurrent.wasm",
      "System.Collections.Immutable.roelzfo964.wasm": "System.Collections.Immutable.wasm",
      "System.Collections.NonGeneric.6o2wb88be1.wasm": "System.Collections.NonGeneric.wasm",
      "System.Collections.Specialized.2yggulfrt1.wasm": "System.Collections.Specialized.wasm",
      "System.Collections.uo098w06k5.wasm": "System.Collections.wasm",
      "System.ComponentModel.Annotations.foj26mfbbx.wasm": "System.ComponentModel.Annotations.wasm",
      "System.ComponentModel.Primitives.mfnqi4sumx.wasm": "System.ComponentModel.Primitives.wasm",
      "System.ComponentModel.TypeConverter.ded2tzoydc.wasm": "System.ComponentModel.TypeConverter.wasm",
      "System.ComponentModel.076m38u6l8.wasm": "System.ComponentModel.wasm",
      "System.Console.byg47owmg6.wasm": "System.Console.wasm",
      "System.Diagnostics.DiagnosticSource.ps3c82qvas.wasm": "System.Diagnostics.DiagnosticSource.wasm",
      "System.IO.Pipelines.7s27r4gsva.wasm": "System.IO.Pipelines.wasm",
      "System.Linq.Expressions.ccv33hbvy1.wasm": "System.Linq.Expressions.wasm",
      "System.Linq.azd6nc5efr.wasm": "System.Linq.wasm",
      "System.Memory.gxk30wm3qo.wasm": "System.Memory.wasm",
      "System.Net.Http.Json.vjlz29vsvf.wasm": "System.Net.Http.Json.wasm",
      "System.Net.Http.v1i9fzm3ys.wasm": "System.Net.Http.wasm",
      "System.Net.Primitives.9x72ktbyas.wasm": "System.Net.Primitives.wasm",
      "System.ObjectModel.wgm2i2b0yp.wasm": "System.ObjectModel.wasm",
      "System.Private.CoreLib.oafhpr8pup.wasm": "System.Private.CoreLib.wasm",
      "System.Private.Uri.2epf8i5mq7.wasm": "System.Private.Uri.wasm",
      "System.Runtime.InteropServices.JavaScript.era55l3sbb.wasm": "System.Runtime.InteropServices.JavaScript.wasm",
      "System.Runtime.Serialization.Primitives.6wjui9dnma.wasm": "System.Runtime.Serialization.Primitives.wasm",
      "System.Runtime.yt2ovicwmn.wasm": "System.Runtime.wasm",
      "System.Text.Encodings.Web.wmi2z5c0zd.wasm": "System.Text.Encodings.Web.wasm",
      "System.Text.Json.vzkk8aua57.wasm": "System.Text.Json.wasm",
      "System.Text.RegularExpressions.6r5snl15sy.wasm": "System.Text.RegularExpressions.wasm",
      "System.f0fr8djds0.wasm": "System.wasm",
      "dotnet.js": "dotnet.js",
      "dotnet.native.hvg7u8bimp.js": "dotnet.native.js",
      "dotnet.native.3c4wvb350q.wasm": "dotnet.native.wasm",
      "dotnet.runtime.cymp1amu5g.js": "dotnet.runtime.js",
      "icudt_CJK.tjcz0u77k5.dat": "icudt_CJK.dat",
      "icudt_EFIGS.tptq2av103.dat": "icudt_EFIGS.dat",
      "icudt_no_CJK.lfu7j35m59.dat": "icudt_no_CJK.dat"
    },
    "jsModuleNative": {
      "dotnet.native.hvg7u8bimp.js": "sha256-LX9rFEWGVxhkOkAVPG0w5RxPwzPBlEUz6dQNjWS7M+M="
    },
    "jsModuleRuntime": {
      "dotnet.runtime.cymp1amu5g.js": "sha256-dCmS9Zx4egtLYSUgTI3R6gMS+Yg8MkzxW1CgEMJKAEw="
    },
    "wasmNative": {
      "dotnet.native.3c4wvb350q.wasm": "sha256-89jyB8DlCnV2BPMV477jOe1Sm0WXwVf8RuoSPsj4Ym8="
    },
    "icu": {
      "icudt_CJK.tjcz0u77k5.dat": "sha256-SZLtQnRc0JkwqHab0VUVP7T3uBPSeYzxzDnpxPpUnHk=",
      "icudt_EFIGS.tptq2av103.dat": "sha256-8fItetYY8kQ0ww6oxwTLiT3oXlBwHKumbeP2pRF4yTc=",
      "icudt_no_CJK.lfu7j35m59.dat": "sha256-L7sV7NEYP37/Qr2FPCePo5cJqRgTXRwGHuwF5Q+0Nfs="
    },
    "coreAssembly": {
      "System.Private.CoreLib.oafhpr8pup.wasm": "sha256-UNPEgyJ4o4be0vU8+yrQ8eotmycA4Qv4uzWT0dcbKZA=",
      "System.Runtime.InteropServices.JavaScript.era55l3sbb.wasm": "sha256-uo4WQ39eiOB+w/weMzCVCfXQey09VlzpTm+e6aR83IA="
    },
    "assembly": {
      "Microsoft.AspNetCore.Components.Forms.td9x62u7gn.wasm": "sha256-wVs6q9ZMXR4514km2lExRnAT+qFLJHCGEWKLNz129o4=",
      "Microsoft.AspNetCore.Components.1lkau6dtgw.wasm": "sha256-tUzZkEl2GWE5/DiwQ+yfk7BLFPNMxrwC5nvvdIh7uCo=",
      "Microsoft.AspNetCore.Components.Web.0ss19v5jlo.wasm": "sha256-8NxQOE4F4+B/yRtrb9ccFg/9G5NB5YJiORfUZWorjfA=",
      "Microsoft.AspNetCore.Components.WebAssembly.ifqb5azqz6.wasm": "sha256-jpe/O0apNqld0EBC+ivtGoIEr5grmWtOjWy/2rKiXM8=",
      "Microsoft.Extensions.Configuration.Abstractions.n3roazub70.wasm": "sha256-M/V9DIZ9otM7/qEt+xn3wagkoRiLOf4JMPyDoo6WUM8=",
      "Microsoft.Extensions.Configuration.Json.jgtmx19396.wasm": "sha256-XQykit2HYxnB0emmOc5bra6XuZq3KgCfazi8kFAErDs=",
      "Microsoft.Extensions.Configuration.7sm4vp77d1.wasm": "sha256-V/8lrAHQfJYsJtV+bKRHL6fmMFhJhAOyoTNfGTbwTdQ=",
      "Microsoft.Extensions.DependencyInjection.Abstractions.hhm8pai5l9.wasm": "sha256-1aQQqs8+B9BBzI7Wyps24LsbWtd37n8OVazTngpH9Hw=",
      "Microsoft.Extensions.DependencyInjection.g0r86u4i0h.wasm": "sha256-wPj/fOeoE7JKOgIYh6OIvl/k3Iw6EPDmmXDjtnQ6rJk=",
      "Microsoft.Extensions.Localization.Abstractions.sjbuahyqim.wasm": "sha256-CJyIxPF5PfWuVePen071zhkTR7TUT111kycpX32WTr0=",
      "Microsoft.Extensions.Localization.wgdl21ygqt.wasm": "sha256-kMLgnUXyCK3PjWaFVpQGP59lzJkRYIrR9nxlovntXE0=",
      "Microsoft.Extensions.Logging.Abstractions.038440qxfw.wasm": "sha256-FJp5EFYj5KS5H3Aw/osLUc7g0geeK11ecpRwLn4aUns=",
      "Microsoft.Extensions.Logging.km3zhtnk76.wasm": "sha256-5E3YJsqbWNbv+OJiZ1kCoV5czf1fXeUBZBKig0eHQKs=",
      "Microsoft.Extensions.Options.x25gjdmbax.wasm": "sha256-ueRCTgiDMRoeRGmcGybrwwZ5wIj057NNM45ToRsvRcU=",
      "Microsoft.Extensions.Primitives.4dxofymb0o.wasm": "sha256-GOr7jc/eCieZrQYoXRn79eLSsesIfFB55wQZIVTSNIY=",
      "Microsoft.JSInterop.to13l1w5p5.wasm": "sha256-s7vy7GhB9lWtwzOXRc3iGonghQTfdnhlRy2xRTUrBQA=",
      "Microsoft.JSInterop.WebAssembly.p386u0jty9.wasm": "sha256-hbzWuXrlepIqY/y+nQ2ZAFer2/njy1dc+Y4LUaAaL5E=",
      "MudBlazor.dmkh4jnd06.wasm": "sha256-Wx1nwVX2miDD2clsMO+IiqGh4NAHmA+0a4rGvkvHmJs=",
      "Portfolio.hv43xg6fnv.wasm": "sha256-k6NyMU9s3efGABtIsPqJl+46lIQBvIqk0PUXsFiQ2mU=",
      "System.Collections.Concurrent.vvprmz0u6g.wasm": "sha256-NYISmYscGJvmyykC3OqZ7NuNdSG4NsWgY06L5VLX0BI=",
      "System.Collections.Immutable.roelzfo964.wasm": "sha256-m5zvTU4twKVgLf89H4wPHD4XA33BHzYqwCpnSW4qphk=",
      "System.Collections.NonGeneric.6o2wb88be1.wasm": "sha256-hiCNLBMli9ZrBjl0l9NVvcXG36xkGJF/znLqDS6yYxs=",
      "System.Collections.Specialized.2yggulfrt1.wasm": "sha256-yrvfqr/qfyZGLNTB9/Af90hkHxTszeU7DmF53S4e1OY=",
      "System.Collections.uo098w06k5.wasm": "sha256-QowacXZ2zZnEaCcFxP1uJHg+0zoppL1X2bamnHIJ++g=",
      "System.ComponentModel.Annotations.foj26mfbbx.wasm": "sha256-4aHcSkszORnKRzohOzoe9X7evNPMZRsmEmErilxmzVc=",
      "System.ComponentModel.Primitives.mfnqi4sumx.wasm": "sha256-3uTpnjOOXmDwN1jU1Ub1dbR7ZtHtNIluSi1eYDFYVkE=",
      "System.ComponentModel.TypeConverter.ded2tzoydc.wasm": "sha256-q6bXRiNh5S271pJ5k36YxpNPbOGWHfMNsKa2J/fcBpI=",
      "System.ComponentModel.076m38u6l8.wasm": "sha256-JNR/o2tUFaDeOk9pghPZD2sAdWEKA2OUJ2ONln9UeD0=",
      "System.Console.byg47owmg6.wasm": "sha256-LYoWBWno4x/iOIGLiU6bX8N2h9cZd/5gOmy2uR7Rl0I=",
      "System.Diagnostics.DiagnosticSource.ps3c82qvas.wasm": "sha256-x7GpRObgn1vqZTVSQPKWaJmi89DhNfSOuwKn+3FVG+Q=",
      "System.IO.Pipelines.7s27r4gsva.wasm": "sha256-15SajmTPgXpuKhgu5FlPAA/Qt8kpTUw5n4xyzUdwPKo=",
      "System.Linq.Expressions.ccv33hbvy1.wasm": "sha256-lAcWW3SpN8KfR3dQxQiGq6Zj3KwJ++X0hezx3krsGVE=",
      "System.Linq.azd6nc5efr.wasm": "sha256-RoN/tHcU/3w0/JC2qdUaOjOb82go5TcymAAcosPjngg=",
      "System.Memory.gxk30wm3qo.wasm": "sha256-tCznIAaQdysSsBlri4JhpkOJQ4Nhsopc01TKAJP/ByY=",
      "System.Net.Http.Json.vjlz29vsvf.wasm": "sha256-JbJ2djTUjcn+vHDxZU4Fh5gSsot0Vfh9Cbtw0PsxIUE=",
      "System.Net.Http.v1i9fzm3ys.wasm": "sha256-XUHM4qdaE63NBtYEp0YnWBwvymO9oTOHIjh/zyYg1jA=",
      "System.Net.Primitives.9x72ktbyas.wasm": "sha256-nezaQh05iG5l4rQswqNPl/zET8UwMn5b44CpxdCrhyQ=",
      "System.ObjectModel.wgm2i2b0yp.wasm": "sha256-wNfPvrHDu12m8nAsDGzNZQk23FT+Jj3h9Ewtkzk8Yuc=",
      "System.Private.Uri.2epf8i5mq7.wasm": "sha256-So6iSuGdZ6wqrfRZppQ92qr2XIMf6jBNU3IJz1pb4b8=",
      "System.Runtime.Serialization.Primitives.6wjui9dnma.wasm": "sha256-NmYMQHBLs7lgIXDfLv3qMr2BXadxAMWLjqs3C6djLCw=",
      "System.Runtime.yt2ovicwmn.wasm": "sha256-Vutp1DFYLipBusgt/gAXqTAV1xRcZXgNnfS2z+TP8mY=",
      "System.Text.Encodings.Web.wmi2z5c0zd.wasm": "sha256-KD5saNzkpUD3A/RXlqBthi/qKA3Sk2nZuNvyfL9+EWc=",
      "System.Text.Json.vzkk8aua57.wasm": "sha256-tYi2J82ZK5vE0hMr4Dl9HTCyQdsv86zkj+GA4AanvXU=",
      "System.Text.RegularExpressions.6r5snl15sy.wasm": "sha256-3rgEBrOFL03rgS0sYeUNvEaqx1CXujqCdyz2dB2Z0k0=",
      "System.f0fr8djds0.wasm": "sha256-v1DeJU321NUwk3KJ0Lf8lQA3zwRfrxNommmMBs1s3Gk="
    }
  },
  "cacheBootResources": true,
  "debugLevel": 0,
  "linkerEnabled": true,
  "globalizationMode": "sharded",
  "extensions": {
    "blazor": {}
  }
}